openscad_parser/__init__.py
openscad_parser-0.9.2.dist-info/licenses/LICENSE
openscad_parser-0.9.2.dist-info/METADATA
openscad_parser-0.9.2.dist-info/WHEEL
openscad_parser-0.9.2.dist-info/top_level.txt
openscad_parser-0.9.2.dist-info/RECORD
